{
  "resource": "InterestsInIssues",
  "http_method": "GET",
  "route": "/interests_in_issues/:id",
  "description": "Getting a specific interest in a issue",
  "explanation": null,
  "parameters": [

  ],
  "requests": [
    {
      "request_method": "GET",
      "request_path": "/interests_in_issues/53bd66b76a6942d34d000034",
      "request_body": null,
      "request_headers": {
        "Accept": "application/vnd.api+json",
        "Content-Type": "application/vnd.api+json",
        "Host": "example.org",
        "Cookie": ""
      },
      "request_query_parameters": {
      },
      "request_content_type": "application/vnd.api+json",
      "response_status": 200,
      "response_status_text": "OK",
      "response_body": "{\"interests_in_issues\":[{\"id\":\"53bd66b76a6942d34d000034\",\"issue_id\":\"53bd66b76a6942d34d000033\",\"member_id\":\"53bd66b76a6942d34d000035\"}]}",
      "response_headers": {"Content-Type":"application/vnd.api+json","Content-Length":"136"},
      "response_content_type": "application/vnd.api+json",
      "curl": "curl \"http://localhost:9292/interests_in_issues/53bd66b76a6942d34d000034\" -X GET \\\n\t-H \"Accept: application/vnd.api+json\" \\\n\t-H \"Content-Type: application/vnd.api+json\" \\\n\t-H \"Host: example.org\" \\\n\t-H \"Cookie: \""
}
  ]
}